{
  "book": "PSA",
  "chapter": "087",
  "verses": {
    "1": [
      {
        "text": "A",
        "start": 0.0,
        "end": 3.3,
        "score": 1.0
      },
      {
        "text": "Psalm",
        "start": 3.3,
        "end": 3.66,
        "score": 0.139
      },
      {
        "text": "of",
        "start": 3.82,
        "end": 3.9,
        "score": 0.124
      },
      {
        "text": "the",
        "start": 3.96,
        "end": 4.04,
        "score": 0.187
      },
      {
        "text": "sons",
        "start": 4.14,
        "end": 4.42,
        "score": 0.306
      },
      {
        "text": "of",
        "start": 4.46,
        "end": 4.54,
        "score": 0.322
      },
      {
        "text": "Korah",
        "start": 4.72,
        "end": 5.02,
        "score": 0.38
      },
      {
        "text": "A",
        "start": 5.02,
        "end": 5.8,
        "score": 1.0
      },
      {
        "text": "song",
        "start": 5.8,
        "end": 6.2,
        "score": 0.269
      }
    ],
    "2": [
      {
        "text": "The",
        "start": 8.44,
        "end": 8.54,
        "score": 0.986
      },
      {
        "text": "LORD",
        "start": 8.54,
        "end": 15.34,
        "score": 1.0
      },
      {
        "text": "loves",
        "start": 15.34,
        "end": 15.56,
        "score": 0.373
      },
      {
        "text": "the",
        "start": 15.58,
        "end": 15.74,
        "score": 0.333
      },
      {
        "text": "gates",
        "start": 15.84,
        "end": 16.08,
        "score": 0.2
      },
      {
        "text": "of",
        "start": 16.14,
        "end": 16.22,
        "score": 1.0
      },
      {
        "text": "Zion",
        "start": 16.38,
        "end": 16.7,
        "score": 0.333
      }
    ],
    "3": [
      {
        "text": "Glorious",
        "start": 17.6,
        "end": 18.06,
        "score": 1.0
      },
      {
        "text": "things",
        "start": 18.14,
        "end": 18.56,
        "score": 0.971
      },
      {
        "text": "are",
        "start": 18.7,
        "end": 18.84,
        "score": 0.912
      },
      {
        "text": "ascribed",
        "start": 18.86,
        "end": 19.48,
        "score": 0.976
      },
      {
        "text": "to",
        "start": 19.58,
        "end": 19.66,
        "score": 0.998
      },
      {
        "text": "you",
        "start": 19.8,
        "end": 19.94,
        "score": 0.979
      }
    ],
    "4": [
      {
        "text": "I",
        "start": 19.94,
        "end": 32.78,
        "score": 1.0
      },
      {
        "text": "will",
        "start": 32.78,
        "end": 33.08,
        "score": 0.25
      },
      {
        "text": "mention",
        "start": 33.08,
        "end": 33.54,
        "score": 0.418
      },
      {
        "text": "Rahab",
        "start": 33.54,
        "end": 34.5,
        "score": 0.25
      }
    ],
    "5": [
      {
        "text": "And",
        "start": 34.52,
        "end": 34.58,
        "score": 0.999
      },
      {
        "text": "it",
        "start": 34.7,
        "end": 34.8,
        "score": 0.999
      },
      {
        "text": "will",
        "start": 34.86,
        "end": 35.0,
        "score": 0.99
      },
      {
        "text": "be",
        "start": 35.04,
        "end": 35.1,
        "score": 0.999
      },
      {
        "text": "said",
        "start": 35.26,
        "end": 35.46,
        "score": 0.954
      },
      {
        "text": "of",
        "start": 35.5,
        "end": 35.58,
        "score": 0.999
      },
      {
        "text": "Zion",
        "start": 35.86,
        "end": 36.06,
        "score": 0.976
      }
    ],
    "6": [
      {
        "text": "The",
        "start": 36.66,
        "end": 36.74,
        "score": 0.436
      },
      {
        "text": "LORD",
        "start": 36.74,
        "end": 43.9,
        "score": 1.0
      },
      {
        "text": "will",
        "start": 43.9,
        "end": 44.04,
        "score": 0.969
      },
      {
        "text": "record",
        "start": 44.1,
        "end": 44.56,
        "score": 0.998
      },
      {
        "text": "in",
        "start": 44.68,
        "end": 44.74,
        "score": 0.999
      },
      {
        "text": "the",
        "start": 44.76,
        "end": 44.84,
        "score": 0.998
      },
      {
        "text": "register",
        "start": 44.9,
        "end": 45.37,
        "score": 0.92
      },
      {
        "text": "of",
        "start": 45.43,
        "end": 45.49,
        "score": 0.999
      },
      {
        "text": "the",
        "start": 45.53,
        "end": 45.63,
        "score": 0.943
      },
      {
        "text": "peoples",
        "start": 45.69,
        "end": 49.47,
        "score": 0.993
      }
    ],
    "7": [
      {
        "text": "Singers",
        "start": 49.53,
        "end": 49.91,
        "score": 0.969
      },
      {
        "text": "and",
        "start": 50.05,
        "end": 50.19,
        "score": 0.929
      },
      {
        "text": "pipers",
        "start": 50.27,
        "end": 50.73,
        "score": 0.95
      },
      {
        "text": "will",
        "start": 50.79,
        "end": 50.95,
        "score": 0.959
      },
      {
        "text": "proclaim",
        "start": 50.99,
        "end": 51.53,
        "score": 0.972
      }
    ]
  }
}